apimatic_open_weather_sdk-1.0.0.dist-info/licenses/LICENSE
openweathermap/__init__.py
openweathermap/api_helper.py
openweathermap/configuration.py
openweathermap/openweathermap_client.py
openweathermap/controllers/__init__.py
openweathermap/controllers/api_controller.py
openweathermap/controllers/base_controller.py
openweathermap/exceptions/__init__.py
openweathermap/exceptions/api_exception.py
openweathermap/http/__init__.py
openweathermap/http/http_call_back.py
openweathermap/http/http_method_enum.py
openweathermap/http/http_request.py
openweathermap/http/http_response.py
openweathermap/models/__init__.py
openweathermap/models/clouds.py
openweathermap/models/coord.py
openweathermap/models/main.py
openweathermap/models/rain.py
openweathermap/models/snow.py
openweathermap/models/successful_response.py
openweathermap/models/sys.py
openweathermap/models/weather.py
openweathermap/models/wind.py
openweathermap/utilities/__init__.py
openweathermap/utilities/file_wrapper.py
apimatic_open_weather_sdk-1.0.0.dist-info/METADATA
apimatic_open_weather_sdk-1.0.0.dist-info/WHEEL
apimatic_open_weather_sdk-1.0.0.dist-info/top_level.txt
apimatic_open_weather_sdk-1.0.0.dist-info/RECORD
